mavis/__init__.py
mavis/breakpoint.py
mavis/config.py
mavis/constants.py
mavis/error.py
mavis/interval.py
mavis/main.py
mavis/overlay.py
mavis/py.typed
mavis/types.py
mavis/util.py
mavis/annotate/__init__.py
mavis/annotate/annotations_schema.json
mavis/annotate/base.py
mavis/annotate/constants.py
mavis/annotate/file_io.py
mavis/annotate/fusion.py
mavis/annotate/genomic.py
mavis/annotate/main.py
mavis/annotate/protein.py
mavis/annotate/splicing.py
mavis/annotate/variant.py
mavis/bam/__init__.py
mavis/bam/cache.py
mavis/bam/cigar.py
mavis/bam/read.py
mavis/bam/stats.py
mavis/cluster/__init__.py
mavis/cluster/cluster.py
mavis/cluster/main.py
mavis/convert/__init__.py
mavis/convert/arriba.py
mavis/convert/breakdancer.py
mavis/convert/chimerascan.py
mavis/convert/cnvnator.py
mavis/convert/constants.py
mavis/convert/starfusion.py
mavis/convert/straglr.py
mavis/convert/transabyss.py
mavis/convert/vcf.py
mavis/illustrate/__init__.py
mavis/illustrate/constants.py
mavis/illustrate/diagram.py
mavis/illustrate/elements.py
mavis/illustrate/scatter.py
mavis/illustrate/util.py
mavis/pairing/__init__.py
mavis/pairing/constants.py
mavis/pairing/main.py
mavis/pairing/pairing.py
mavis/summary/__init__.py
mavis/summary/constants.py
mavis/summary/main.py
mavis/summary/summary.py
mavis/validate/__init__.py
mavis/validate/align.py
mavis/validate/assemble.py
mavis/validate/base.py
mavis/validate/blat.py
mavis/validate/call.py
mavis/validate/constants.py
mavis/validate/evidence.py
mavis/validate/gather.py
mavis/validate/main.py
tools/__init__.py
tools/calculate_ref_alt_counts.py
tools/convert_annotations_format.py
tools/convert_dgv.py
tools/find_repeats.py
tools/generate_ensembl_json.py
mavis-3.1.2.dist-info/LICENSE
mavis-3.1.2.dist-info/METADATA
mavis-3.1.2.dist-info/WHEEL
mavis-3.1.2.dist-info/dependency_links.txt
mavis-3.1.2.dist-info/entry_points.txt
mavis-3.1.2.dist-info/top_level.txt
mavis-3.1.2.dist-info/RECORD
