Metadata-Version: 2.1
Name: mavis
Version: 3.1.2
Summary: A Structural Variant Post-Processing Package
Home-page: https://github.com/bcgsc/mavis.git
Download-URL: https://github.com/bcgsc/mavis/archive/v2.2.10.tar.gz
Author: Caralyn Reisle
Author-email: creisle@bcgsc.ca
Maintainer: mavis
Maintainer-email: mavis@bcgsc.ca
Project-URL: mavis, http://mavis.bcgsc.ca
Requires-Python: >=3.7
License-File: LICENSE
Requires-Dist: biopython <1.78,>=1.70
Requires-Dist: braceexpand ==0.1.2
Requires-Dist: colour
Requires-Dist: Distance >=0.1.3
Requires-Dist: mavis-config <2.0.0,>=1.2.2
Requires-Dist: networkx <3,>=2.5
Requires-Dist: numpy >=1.13.1
Requires-Dist: pandas <2,>=1.1
Requires-Dist: pysam
Requires-Dist: Shapely >=1.6.4.post1
Requires-Dist: shortuuid >=0.5.0
Requires-Dist: svgwrite
Requires-Dist: typing-extensions >=4
Provides-Extra: deploy
Requires-Dist: twine ; extra == 'deploy'
Requires-Dist: wheel ; extra == 'deploy'
Provides-Extra: dev
Requires-Dist: black ; extra == 'dev'
Requires-Dist: flake8 ; extra == 'dev'
Requires-Dist: isort ; extra == 'dev'
Requires-Dist: twine ; extra == 'dev'
Requires-Dist: wheel ; extra == 'dev'
Requires-Dist: timeout-decorator >=0.3.3 ; extra == 'dev'
Requires-Dist: coverage >=4.2 ; extra == 'dev'
Requires-Dist: pycodestyle >=2.3.1 ; extra == 'dev'
Requires-Dist: pytest ; extra == 'dev'
Requires-Dist: pytest-cov ; extra == 'dev'
Requires-Dist: pytest-xdist ; extra == 'dev'
Requires-Dist: mkdocs <2,>=1.1.2 ; extra == 'dev'
Requires-Dist: markdown-refdocs ; extra == 'dev'
Requires-Dist: mkdocs-material >=5.4.0 ; extra == 'dev'
Requires-Dist: markdown-include ; extra == 'dev'
Requires-Dist: mkdocs-simple-hooks >=0.1.2 ; extra == 'dev'
Requires-Dist: types-setuptools <58,>=57.4.7 ; extra == 'dev'
Provides-Extra: doc
Requires-Dist: mkdocs >=1.1.2 ; extra == 'doc'
Requires-Dist: markdown-refdocs ; extra == 'doc'
Requires-Dist: mkdocs-material >=5.4.0 ; extra == 'doc'
Requires-Dist: markdown-include ; extra == 'doc'
Requires-Dist: mkdocs-simple-hooks >=0.1.2 ; extra == 'doc'
Requires-Dist: mkdocs-awesome-pages-plugin ; extra == 'doc'
Provides-Extra: test
Requires-Dist: timeout-decorator >=0.3.3 ; extra == 'test'
Requires-Dist: coverage >=4.2 ; extra == 'test'
Requires-Dist: pycodestyle >=2.3.1 ; extra == 'test'
Requires-Dist: pytest ; extra == 'test'
Requires-Dist: pytest-cov ; extra == 'test'
Provides-Extra: tools
Requires-Dist: pyensembl ; extra == 'tools'
Requires-Dist: simplejson ; extra == 'tools'
Requires-Dist: requests ; extra == 'tools'
